setup.py
django_static_upstream.egg-info/PKG-INFO
django_static_upstream.egg-info/SOURCES.txt
django_static_upstream.egg-info/dependency_links.txt
django_static_upstream.egg-info/top_level.txt
supstream/__init__.py
supstream/__version__.py
supstream/middleware.py
supstream/utils.py
supstream/views.py