Metadata-Version: 1.0
Name: django-static-upstream
Version: 0.1.1
Summary: Django package to handle (serve, reference, compile) static files
Home-page: https://github.com/yaniv-aknin/supstream
Author: Yaniv Aknin
Author-email: yaniv@aknin.name
License: MIT
Platform: UNKNOWN
